[{
  "dateTime" : "11/08/22 00:00:00",
  "value" : "6"
},{
  "dateTime" : "11/09/22 00:00:00",
  "value" : "8"
},{
  "dateTime" : "11/10/22 00:00:00",
  "value" : "0"
},{
  "dateTime" : "11/11/22 00:00:00",
  "value" : "54"
},{
  "dateTime" : "11/12/22 00:00:00",
  "value" : "0"
},{
  "dateTime" : "11/13/22 00:00:00",
  "value" : "0"
},{
  "dateTime" : "11/14/22 00:00:00",
  "value" : "2"
},{
  "dateTime" : "11/15/22 00:00:00",
  "value" : "9"
},{
  "dateTime" : "11/16/22 00:00:00",
  "value" : "6"
},{
  "dateTime" : "11/17/22 00:00:00",
  "value" : "1"
},{
  "dateTime" : "11/18/22 00:00:00",
  "value" : "0"
},{
  "dateTime" : "11/19/22 00:00:00",
  "value" : "0"
},{
  "dateTime" : "11/20/22 00:00:00",
  "value" : "0"
},{
  "dateTime" : "11/21/22 00:00:00",
  "value" : "2"
},{
  "dateTime" : "11/22/22 00:00:00",
  "value" : "0"
},{
  "dateTime" : "11/23/22 00:00:00",
  "value" : "0"
},{
  "dateTime" : "11/24/22 00:00:00",
  "value" : "13"
},{
  "dateTime" : "11/25/22 00:00:00",
  "value" : "3"
},{
  "dateTime" : "11/26/22 00:00:00",
  "value" : "0"
},{
  "dateTime" : "11/27/22 00:00:00",
  "value" : "0"
},{
  "dateTime" : "11/28/22 00:00:00",
  "value" : "0"
},{
  "dateTime" : "11/29/22 00:00:00",
  "value" : "6"
},{
  "dateTime" : "11/30/22 00:00:00",
  "value" : "0"
},{
  "dateTime" : "12/01/22 00:00:00",
  "value" : "0"
},{
  "dateTime" : "12/02/22 00:00:00",
  "value" : "0"
},{
  "dateTime" : "12/03/22 00:00:00",
  "value" : "5"
},{
  "dateTime" : "12/04/22 00:00:00",
  "value" : "31"
},{
  "dateTime" : "12/05/22 00:00:00",
  "value" : "7"
},{
  "dateTime" : "12/06/22 00:00:00",
  "value" : "0"
},{
  "dateTime" : "12/07/22 00:00:00",
  "value" : "0"
}]